odoo9_addon_base_user_gravatar-9.0.1.0.0.99.dev16-py2.7-nspkg.pth
odoo9_addon_base_user_gravatar-9.0.1.0.0.99.dev16.dist-info/DESCRIPTION.rst
odoo9_addon_base_user_gravatar-9.0.1.0.0.99.dev16.dist-info/METADATA
odoo9_addon_base_user_gravatar-9.0.1.0.0.99.dev16.dist-info/RECORD
odoo9_addon_base_user_gravatar-9.0.1.0.0.99.dev16.dist-info/WHEEL
odoo9_addon_base_user_gravatar-9.0.1.0.0.99.dev16.dist-info/metadata.json
odoo9_addon_base_user_gravatar-9.0.1.0.0.99.dev16.dist-info/namespace_packages.txt
odoo9_addon_base_user_gravatar-9.0.1.0.0.99.dev16.dist-info/top_level.txt
odoo_addons/base_user_gravatar/README.rst
odoo_addons/base_user_gravatar/__init__.py
odoo_addons/base_user_gravatar/__openerp__.py
odoo_addons/base_user_gravatar/i18n/ar.po
odoo_addons/base_user_gravatar/i18n/base_user_gravatar.pot
odoo_addons/base_user_gravatar/i18n/ca.po
odoo_addons/base_user_gravatar/i18n/de.po
odoo_addons/base_user_gravatar/i18n/el_GR.po
odoo_addons/base_user_gravatar/i18n/es.po
odoo_addons/base_user_gravatar/i18n/es_ES.po
odoo_addons/base_user_gravatar/i18n/fi.po
odoo_addons/base_user_gravatar/i18n/fr.po
odoo_addons/base_user_gravatar/i18n/fr_CH.po
odoo_addons/base_user_gravatar/i18n/hr.po
odoo_addons/base_user_gravatar/i18n/hr_HR.po
odoo_addons/base_user_gravatar/i18n/it.po
odoo_addons/base_user_gravatar/i18n/nl.po
odoo_addons/base_user_gravatar/i18n/pt_BR.po
odoo_addons/base_user_gravatar/i18n/sl.po
odoo_addons/base_user_gravatar/i18n/tr.po
odoo_addons/base_user_gravatar/i18n/tr_TR.po
odoo_addons/base_user_gravatar/i18n/zh_CN.po
odoo_addons/base_user_gravatar/models/__init__.py
odoo_addons/base_user_gravatar/models/res_users.py
odoo_addons/base_user_gravatar/static/description/icon.png
odoo_addons/base_user_gravatar/tests/__init__.py
odoo_addons/base_user_gravatar/tests/test_res_users.py
odoo_addons/base_user_gravatar/views/res_users_view.xml
