Metadata-Version: 2.0
Name: odoo9-addon-base-user-gravatar
Version: 9.0.1.0.0.99.dev16
Summary: Synchronize Gravatar Image
Home-page: http://www.endikaiglesias.com/
Author: LasLabs, Endika Iglesias, Odoo Community Association (OCA)
Author-email: support@odoo-community.org
License: AGPL-3
Platform: UNKNOWN
Classifier: Programming Language :: Python
Classifier: Framework :: Odoo
Classifier: License :: OSI Approved :: GNU Affero General Public License v3
Requires-Python: ~=2.7
Requires-Dist: odoo (<9.1a,>=9.0a)
